disjoint_union/__init__.py
disjoint_union/disjoint_union.py
disjoint_union-0.5.0.dist-info/LICENSE
disjoint_union-0.5.0.dist-info/METADATA
disjoint_union-0.5.0.dist-info/WHEEL
disjoint_union-0.5.0.dist-info/top_level.txt
disjoint_union-0.5.0.dist-info/RECORD
