Metadata-Version: 2.1
Name: disjoint_union
Version: 0.5.0
Summary: Disjoint set / union find algorithm
Home-page: https://github.com/alexdelorenzo/disjoint_set
Author: Alex DeLorenzo
License: AGPL-3.0
Platform: UNKNOWN
Requires-Python: >=3.10
License-File: LICENSE
